zookeeper/__init__.py
zookeeper/__main__.py
stingray_zookeeper-0.1.0.dist-info/entry_points.txt
stingray_zookeeper-0.1.0.dist-info/LICENSE
stingray_zookeeper-0.1.0.dist-info/WHEEL
stingray_zookeeper-0.1.0.dist-info/METADATA
stingray_zookeeper-0.1.0.dist-info/RECORD
