Metadata-Version: 2.1
Name: stingray-zookeeper
Version: 0.1.0
Summary: Zookeeper is a command-line utility for managing Stingray.
Home-page: https://github.com/regulad/zookeeper
License: GPLv3
Author: Parker Wahle
Author-email: parkeredwardwahle2017@gmail.com
Requires-Python: >=3.10,<4.0
Classifier: License :: Other/Proprietary License
Classifier: Programming Language :: Python :: 3
Classifier: Programming Language :: Python :: 3.10
Requires-Dist: nginxproxymanager (>=0.1.0,<0.2.0)
Requires-Dist: py-dactyl (>=2.0.0,<3.0.0)
Project-URL: Repository, https://github.com/regulad/zookeeper
